{"format":2,"version":"6.1.1","globals":"fe8a7800433de90547eaa9733aabe76d","files":{"d_a1905ddbc43051a0___init___py":{"hash":"73f58637f1c5aaf6ae1fd2236c636a1a","index":{"nums":[0,1,4,4,0,0,0,0],"html_filename":"d_a1905ddbc43051a0___init___py.html","relative_filename":"qdscreen/__init__.py"}},"d_a1905ddbc43051a0__version_py":{"hash":"bb5eb4809e183a9cf8f64f8a33a741de","index":{"nums":[0,1,2,0,0,0,0,0],"html_filename":"d_a1905ddbc43051a0__version_py.html","relative_filename":"qdscreen/_version.py"}},"d_a1905ddbc43051a0_compat_py":{"hash":"6bc635cb3674ca50327e519a01dfeb42","index":{"nums":[0,1,81,4,64,28,2,26],"html_filename":"d_a1905ddbc43051a0_compat_py.html","relative_filename":"qdscreen/compat.py"}},"d_a1905ddbc43051a0_main_py":{"hash":"6b1dfa92413353a8735c2f91b277ac93","index":{"nums":[0,1,467,0,58,216,33,49],"html_filename":"d_a1905ddbc43051a0_main_py.html","relative_filename":"qdscreen/main.py"}},"d_a1905ddbc43051a0_selector_py":{"hash":"2e99ed1c56496180c6c82db1d1287133","index":{"nums":[0,1,79,0,10,40,9,9],"html_filename":"d_a1905ddbc43051a0_selector_py.html","relative_filename":"qdscreen/selector.py"}},"d_a1905ddbc43051a0_sklearn_py":{"hash":"997f6b21a05f22dbc20609ff19d5c1a5","index":{"nums":[0,1,32,0,5,4,2,2],"html_filename":"d_a1905ddbc43051a0_sklearn_py.html","relative_filename":"qdscreen/sklearn.py"}}}}